MANIFEST.in
README.markdown
setup.py
stricttype/__init__.py
stricttype/stricttype.py
stricttype.egg-info/PKG-INFO
stricttype.egg-info/SOURCES.txt
stricttype.egg-info/dependency_links.txt
stricttype.egg-info/top_level.txt