Metadata-Version: 1.1
Name: stricttype
Version: 0.1
Summary: Python type checker.
Home-page: https://github.com/gennad/stricttype
Author: Gennadiy Zlobin
Author-email: gennad.zlobin@gmail.com
License: MIT License
Download-URL: https://github.com/gennad/stricttype/tarball/master
Keywords: type
Platform: UNKNOWN
Classifier: Intended Audience :: Developers
Classifier: Programming Language :: Python
Requires: python (>= 2.5)
